{
    "bursts": [
        {
            "burstNumber": 1,
            "burstCoordinates": [
                {
                    "x": 8.07,
                    "y": 12.49
                },
                {
                    "x": 17.09,
                    "y": 11.57
                },
                {
                    "x": 14.85,
                    "y": 17.45
                },
                {
                    "x": 9.77,
                    "y": 14.08
                },
                {
                    "x": 14.51,
                    "y": 2.98
                }
            ]
        },
        {
            "burstNumber": 2,
            "burstCoordinates": [
                {
                    "x": 16.09,
                    "y": 2.31
                },
                {
                    "x": 0.82,
                    "y": 18.52
                },
                {
                    "x": 14.54,
                    "y": 12.23
                },
                {
                    "x": 5.5,
                    "y": 11.59
                },
                {
                    "x": 6.79,
                    "y": 1.52
                }
            ]
        },
        {
            "burstNumber": 3,
            "burstCoordinates": [
                {
                    "x": 13.35,
                    "y": 18.68
                },
                {
                    "x": 8.55,
                    "y": 15.06
                },
                {
                    "x": 19.29,
                    "y": 12.23
                },
                {
                    "x": 7.48,
                    "y": 10.65
                },
                {
                    "x": 10.16,
                    "y": 18.98
                }
            ]
        }
    ]
}